<?xml version='1.0' encoding='windows-1252' ?>
<tocdata>
<node label="PART1" >
    <node label="TCPIP" >
	   <node label="IPV4" >
         <node label="Decomposition of an IP Packet" url="PART1/TCPIP_v4/IP_Packet/Flash/IP_Packet.html" />
         <node label="Decomposition of an TCP Packet" url="NULL-page.htm" />
         <node label="Decomposition of an UDP Packet" url="NULL-page.htm" />
         <node label="Decomposition of an ICMP Packet" url="NULL-page.htm" />
       </node>
   	   <node label="IPV6" >
         <node label="TCPIP Ver 6  Overview" url="PART1/TCPIP_v6/IPV6_OverView.htm" />
		 <node label="Introduction" url="PART1/TCPIP_v6/Flash.mx/introduction/introduction.html" > 
		   <node label="IPv6 Features" url="PART1/TCPIP_v6/Flash.mx/introduction/IPv6 Features.html" />
  		   <node label="Differences Between IPv4 and IPv6" url="PART1/TCPIP_v6/Flash.mx/introduction/DifferencesIPv4v6.html" />
		   <node label="IPv6 Packets over LAN Media" url="PART1/TCPIP_v6/Flash.mx/introduction/IPv6_over_LAN.html" />
		   <node label="Microsoft IPv6 Implementations" url="NULL-page.htm" />
		   </node>
		 <node label="IPv6 Addressing" >
		   <node label="The IPv6 Address Space" url="NULL-page.htm" />
		   <node label="IPv6 Address Syntax" url="NULL-page.htm" />
		   <node label="IPv6 Prefixes" url="NULL-page.htm" />
		   <node label="Types of IPv6 Addresses" url="NULL-page.htm" />
		   <node label="Unicast IPv6 Addresses" url="NULL-page.htm" />
  		   <node label="Multicast IPv6 Addresses" url="NULL-page.htm" />
		   <node label="Anycast IPv6 Addresses" url="NULL-page.htm" />
		   <node label="IPv6 Addresses for a Host" url="NULL-page.htm" />
		   <node label="IPv6 Addresses for a Router" url="NULL-page.htm" />
		   <node label="IPv6 Interface Identifiers" url="NULL-page.htm" />
		   <node label="Mapping IPv6 Multicast Addresses to Ethernet Addresses" url="NULL-page.htm" />
		   <node label="IPv6 and DNS" url="NULL-page.htm" />
		   <node label="IPv4 Addresses and IPv6 Equivalents" url="NULL-page.htm" />
		 </node>
		 <node label="IPv6 Header" >
		   <node label="Structure of an IPv6 Packet" url="NULL-page.htm" />
		   <node label="IPv4 Header" url="NULL-page.htm" />
   		   <node label="IPv6 Header" url="NULL-page.htm" />
		   <node label="IPv6 Extension Headers" url="NULL-page.htm" />
		   <node label="IPv6 MTU" url="NULL-page.htm" />
		   <node label="Upper Layer Checksums" url="NULL-page.htm" />
		 </node>
		 <node label="ICMPv6" >
		   <node label="Types of ICMPv6 Messages" url="NULL-page.htm" />
		   <node label="ICMPv6 Header" url="NULL-page.htm" />
   		   <node label="ICMPv6 Error Messages" url="NULL-page.htm" />
		   <node label="ICMPv6 Informational Messages" url="NULL-page.htm" />
		   <node label="Comparing ICMPv4 and ICMPv6 Error Messages" url="NULL-page.htm" />
		   <node label="Path MTU Discovery" url="NULL-page.htm" />
		 </node>	
		 <node label="Multicast Listener Discovery" >
		   <node label="Multicast Listener Query" url="NULL-page.htm" />
		   <node label="Multicast Listener Report" url="NULL-page.htm" />
   		   <node label="Multicast Listener Done" url="NULL-page.htm" />
		 </node>			 	 
		 <node label="Neighbor Discovery" >
		   <node label="Neighbor Discovery Message Format" url="NULL-page.htm" />
		   <node label="Neighbor Discovery Options" url="NULL-page.htm" />
   		   <node label="Neighbor Discovery Messages" url="NULL-page.htm" />
   		   <node label="Neighbor Discovery Processes" url="NULL-page.htm" />  
		 </node>		
		 <node label="Address Autoconfiguration" >
		   <node label="Autoconfigured Address States" url="NULL-page.htm" />
		   <node label="Types of Autoconfiguration" url="NULL-page.htm" />
   		   <node label="Autoconfiguration Process" url="NULL-page.htm" />
		 </node>				   

	   </node>
	</node>
	<node label="SECURITY" >
		   <node label="Windows XP" >
           <node label="Protect your SAM by using System Key" url="PART1/Protect_Sam/Protect_sam.html" />
           <node label="Encryption and Certificate (Recovery)" url="NULL-page.htm" />
           </node>

	</node>

</node>

<node label="PART2" >
  <node label="BROWSER" >
    <node label="Introduction to BROWSER" >
      <node label="Browser (Browse Service Across Multiple Workgroups and Domains)" url="PART2/Browser_pic/Other-htm/across_multiple.htm" />
      <node label="Browser (Browser Announcements)" url="PART2/Browser_pic/Other-htm/announcements.htm" />
      <node label="Browser (Browser Requests)" url="PART2/Browser_pic/Other-htm/browser_requests.htm" />
      <node label="Browser (Browser Shutdown or Failure)" url="PART2/Browser_pic/Other-htm/shutdown_or_failure.htm" />
      <node label="Browser (Number of Browsers in a Domain or Workgroup)" url="PART2/Browser_pic/Other-htm/number_of_browsers.htm" />
      <node label="Browser (Registration and Propagation)" url="PART2/Browser_pic/Other-htm/registration.htm" />
      <node label="Browser (Computers Running Windows for Workgroups, Windows 95, and Windows 98 as Master Browsers)" url="PART2/Browser_pic/Other-htm/computers_running.htm" />
      <node label="Browser Testing Techniques" url="PART2/Browser_pic/Other-htm/testing_techniques.htm" />
    </node>
    <node label="Winteacher.com Browser Service User Guide" url="PART2/Browser_pic/browser-main.htm" />
  </node>
  <node label="DHCP" >
    <node label="Introduction to DHCP" >
      <node label="Administering" >
        <node label="DHCP (Authorizing DHCP servers )  User Guide  " url="PART2/DHCP_PIC/Other-htm/Administering/authorizing.htm" >
          <node label="how_unauthorized_rogue_servers_are_detected" url="PART2/DHCP_PIC/Other-htm/Administering/authorizing.htm#how_unauthorized_rogue_servers_are_detected" />
          <node label="how_dhcp_servers_get_authorized" url="PART2/DHCP_PIC/Other-htm/Administering/authorizing.htm#how_dhcp_servers_get_authorized" />
        </node>
        <node label="DHCP (Interoperability issues)  User Guide  " url="PART2/DHCP_PIC/Other-htm/Administering/interoperability_issues_.htm" />
        <node label="DHCP (Managing DHCP from the command line)  User Guide  " url="PART2/DHCP_PIC/Other-htm/Administering/dhcp_command.htm" />
        <node label="DHCP (Setting up options)  User Guide  " url="PART2/DHCP_PIC/Other-htm/Administering/setting_up_options.htm" />
        <node label="DHCP (Setting up scopes)  User Guide  " url="PART2/DHCP_PIC/Other-htm/Administering/setting_up_scopes.htm" />
      </node>
      <node label="DHCP (Configuring Options) User Guide  " url="PART2/DHCP_PIC/Other-htm/configuring_options.htm" />
      <node label="DHCP (DHCP Database) User Guide  " url="PART2/DHCP_PIC/Other-htm/dhcp_database.htm" />
      <node label="DHCP (DHCP Option Parameters) User Guide  " url="PART2/DHCP_PIC/Other-htm/dhcp_options_parameters.htm" />
      <node label="DHCP (Managing DHCP Options) User Guide  " url="PART2/DHCP_PIC/Other-htm/managing_dhcp_options.htm" />
      <node label="DHCP (Managing SuperScope) User Guide  " url="PART2/DHCP_PIC/Other-htm/Managing_SuperScope.htm" />
      <node label="DHCP (Multicast DHCP) User Guide  " url="PART2/DHCP_PIC/Other-htm/multicast_dhcp.htm" />
      <node label="DHCP (Option Classes) User Guide  " url="PART2/DHCP_PIC/Other-htm/Option_Classes.htm" >
        <node label="KB235272" url="PART2/DHCP_PIC/Other-htm/Option_Classes.htm#KB235272" />
        <node label="KB235273" url="PART2/DHCP_PIC/Other-htm/Option_Classes.htm#KB235273" />
      </node>
      <node label="DHCP (Preventing Address Conflicts) User Guide  " url="PART2/DHCP_PIC/Other-htm/preventing_address_conflicts.htm" />
      <node label="DHCP Lease Process  User Guide  " url="PART2/DHCP_PIC/Other-htm/dhcpleaseprocess.htm" />
      <node label="DHCP  User Guide  " url="PART2/DHCP_PIC/Other-htm/whatisdhcp.htm" />
      <node label="DHCP  User Guide  " url="PART2/DHCP_PIC/Other-htm/dhcpoption_des.htm" />
      <node label="DHCP ( Managing Scopes ) User Guide  " url="PART2/DHCP_PIC/Other-htm/Managing_Scopes.htm" />
      <node label="winteacher.com Troubleshooting DHCP    FARSI" url="PART2/DHCP_PIC/Other-htm/troubleshooting_dhcp.htm" >
        <node label="442" url="PART2/DHCP_PIC/Other-htm/troubleshooting_dhcp.htm#442" />
        <node label="428" url="PART2/DHCP_PIC/Other-htm/troubleshooting_dhcp.htm#428" />
        <node label="431" url="PART2/DHCP_PIC/Other-htm/troubleshooting_dhcp.htm#431" />
        <node label="434" url="PART2/DHCP_PIC/Other-htm/troubleshooting_dhcp.htm#434" />
        <node label="436" url="PART2/DHCP_PIC/Other-htm/troubleshooting_dhcp.htm#436" />
        <node label="439" url="PART2/DHCP_PIC/Other-htm/troubleshooting_dhcp.htm#439" />
        <node label="438" url="PART2/DHCP_PIC/Other-htm/troubleshooting_dhcp.htm#438" />
        <node label="441" url="PART2/DHCP_PIC/Other-htm/troubleshooting_dhcp.htm#441" />
      </node>
    </node>
    <node label="Winteacher.com DHCP  User Guide  " url="PART2/DHCP_PIC/dhcpmain2.htm" />
  </node>
  <node label="DNS" >
    <node label="Introduction to DNS" >
      <node label="DNS Properties-WinsTab-ADSIntegrated Zone" url="PART2/DNS_PIC/other-htm/dns_properties_wins.htm" />
      <node label="DNS Aging and Scavenging of Stale Records  " url="PART2/DNS_PIC/other-htm/aging_and_scavenging.htm" />
      <node label="DNS Dynamic Update and Secure Dynamic Update  " url="PART2/DNS_PIC/other-htm/Dynamic-Secure_Dynamic_Update.htm" />
      <node label="DNS Example of Queries (Query for a Name in the External Namespace)" url="PART2/DNS_PIC/other-htm/example_of__queries_2.htm" />
      <node label="DNS Example of Queries (Query for a Name in the Internal Namespace)" url="PART2/DNS_PIC/other-htm/example_of__queries_1.htm" />
      <node label="DNS Examples of Queries (Query for a Name in the External Namespace of an Organization)" url="PART2/DNS_PIC/other-htm/example_of__queries_3.htm" />
      <node label="DNS Integration with WINS" url="PART2/DNS_PIC/other-htm/Integration_with_WINS.htm" />
      <node label="DNS Internet Access Considerations" url="PART2/DNS_PIC/other-htm/internet_access_considerations.htm" />
      <node label="DNS Interoperability with Other DNS Servers" url="PART2/DNS_PIC/other-htm/interoperability_with_other_dns_servers.htm" />
      <node label="DNS Namespace Planning Example( Language: English)" url="PART2/DNS_PIC/other-htm/Namespace_Planning_Example.htm" />
      <node label="DNS Naming Hosts and Domains language:Farsi" url="PART2/DNS_PIC/other-htm/naming_hosts&amp;domains.htm" />
      <node label="DNS Properties-Name ServersTab-ADSIntegrated Zone" url="PART2/DNS_PIC/other-htm/dns_properties_nameserv.htm" />
      <node label="DNS Properties-SecurityTab-ADSIntegrated Zone" url="PART2/DNS_PIC/other-htm/dns_properties_security.htm" />
      <node label="DNS Properties RoothintsTab" url="PART2/DNS_PIC/other-htm/dns_properties_roothintstab.htm" />
      <node label="DNS Properties ZoneTransfer-ADSIntegrated Zone" url="PART2/DNS_PIC/other-htm/dns_properties_zonetransfer.htm" />
      <node label="DNS Properties  Interfaces Tab" url="PART2/DNS_PIC/other-htm/dns_properties_interfacestab.htm" />
      <node label="DNS Properties   Advanced Tab" url="PART2/DNS_PIC/other-htm/dns_properties__advancedtab.htm" />
      <node label="DNS Properties   Forwarders Tab" url="PART2/DNS_PIC/other-htm/dns_properties__forwarderstab.htm" />
      <node label="Winteacher.com DNS Resource records reference" url="PART2/DNS_PIC/other-htm/records_reference.htm" >
        <node label="txt" url="PART2/DNS_PIC/other-htm/records_reference.htm#txt" />
        <node label="sig" url="PART2/DNS_PIC/other-htm/records_reference.htm#sig" />
        <node label="ptr" url="PART2/DNS_PIC/other-htm/records_reference.htm#ptr" />
        <node label="x25" url="PART2/DNS_PIC/other-htm/records_reference.htm#x25" />
        <node label="rt" url="PART2/DNS_PIC/other-htm/records_reference.htm#rt" />
        <node label="SOA" url="PART2/DNS_PIC/other-htm/records_reference.htm#SOA" />
        <node label="srv" url="PART2/DNS_PIC/other-htm/records_reference.htm#srv" />
        <node label="wks" url="PART2/DNS_PIC/other-htm/records_reference.htm#wks" />
        <node label="rp" url="PART2/DNS_PIC/other-htm/records_reference.htm#rp" />
        <node label="opt" url="PART2/DNS_PIC/other-htm/records_reference.htm#opt" />
        <node label="a" url="PART2/DNS_PIC/other-htm/records_reference.htm#a" />
        <node label="aaaa" url="PART2/DNS_PIC/other-htm/records_reference.htm#aaaa" />
        <node label="afsdb" url="PART2/DNS_PIC/other-htm/records_reference.htm#afsdb" />
        <node label="atma" url="PART2/DNS_PIC/other-htm/records_reference.htm#atma" />
        <node label="hinfo" url="PART2/DNS_PIC/other-htm/records_reference.htm#hinfo" />
        <node label="isdn" url="PART2/DNS_PIC/other-htm/records_reference.htm#isdn" />
        <node label="key" url="PART2/DNS_PIC/other-htm/records_reference.htm#key" />
        <node label="mb" url="PART2/DNS_PIC/other-htm/records_reference.htm#mb" />
        <node label="mg" url="PART2/DNS_PIC/other-htm/records_reference.htm#mg" />
        <node label="minfo" url="PART2/DNS_PIC/other-htm/records_reference.htm#minfo" />
        <node label="mr" url="PART2/DNS_PIC/other-htm/records_reference.htm#mr" />
        <node label="mx" url="PART2/DNS_PIC/other-htm/records_reference.htm#mx" />
        <node label="ns" url="PART2/DNS_PIC/other-htm/records_reference.htm#ns" />
        <node label="nxt" url="PART2/DNS_PIC/other-htm/records_reference.htm#nxt" />
        <node label="cname" url="PART2/DNS_PIC/other-htm/records_reference.htm#cname" />
      </node>
      <node label="DNS Setting Up DNS for Active Directory  " url="PART2/DNS_PIC/other-htm/setting_up_dns_for_ads.htm" />
      <node label="DNS To add a CNAME Resource Records to a zone." url="PART2/DNS_PIC/other-htm/cname_resource_record.htm" />
      <node label="DNS To add a pointer (PTR) resource record to a reverse zone.  " url="PART2/DNS_PIC/other-htm/pointer_resource_record.htm" />
      <node label="DNS Windows 2000 Resolver  " url="PART2/DNS_PIC/other-htm/win2kresolver.htm" />
      <node label="DNS  Active Directory Integration and Multimaster Replication  " url="PART2/DNS_PIC/other-htm/Integration-Multimaster-Replication.htm" />
      <node label="DNS  Properties-GeneralTab-ADSIntegrated Zone" url="PART2/DNS_PIC/other-htm/dns_properties_general.htm" />
      <node label="DNS  To add a host (A) resource record to a zone. Language Farsi" url="PART2/DNS_PIC/other-htm/(a)_resource_record.htm" />
      <node label="DNS You can manually enable or disable aging and scavenging on a per" url="PART2/DNS_PIC/other-htm/DNSCMD.htm" />
    </node>
    <node label="Winteacher.com DNS  " url="PART2/DNS_PIC/dns-main.htm" />
  </node>
  <node label="IPSEC" >
    <node label="Internet Protocol Security (IPSec) ver 4 language:Farsi" url="PART2/IPSEC_PIC/ipsecmain.htm" >
      <node label="a_sag_IPSectopnode" url="PART2/IPSEC_PIC/ipsecmain.htm#a_sag_IPSectopnode" />
      <node label="a_sag_IPSecfeatures" url="PART2/IPSEC_PIC/ipsecmain.htm#a_sag_IPSecfeatures" />
    </node>
    <node label="Understanding Internet Protocol Security" >
      <node label="Understanding Internet Protocol Security language:Farsi" url="PART2/IPSEC_PIC/Understanding_Internet_Protocol_Security/understanding_ipsec.htm" >
        <node label="H2_358269799" url="PART2/IPSEC_PIC/Understanding_Internet_Protocol_Security/understanding_ipsec.htm#H2_358269799" />
        <node label="a_sag_IPSectunnel" url="PART2/IPSEC_PIC/Understanding_Internet_Protocol_Security/understanding_ipsec.htm#a_sag_IPSectunnel" />
        <node label="H2_358270729" url="PART2/IPSEC_PIC/Understanding_Internet_Protocol_Security/understanding_ipsec.htm#H2_358270729" />
        <node label="a_sag_IPSecisakmp" url="PART2/IPSEC_PIC/Understanding_Internet_Protocol_Security/understanding_ipsec.htm#a_sag_IPSecisakmp" />
        <node label="a_sag_IPSecpolicyagn" url="PART2/IPSEC_PIC/Understanding_Internet_Protocol_Security/understanding_ipsec.htm#a_sag_IPSecpolicyagn" />
        <node label="a_sag_IPSecfeatures" url="PART2/IPSEC_PIC/Understanding_Internet_Protocol_Security/understanding_ipsec.htm#a_sag_IPSecfeatures" />
        <node label="a_sag_IPSecstds-refs" url="PART2/IPSEC_PIC/Understanding_Internet_Protocol_Security/understanding_ipsec.htm#a_sag_IPSecstds-refs" />
        <node label="a_sag_IPSecsecprotocols" url="PART2/IPSEC_PIC/Understanding_Internet_Protocol_Security/understanding_ipsec.htm#a_sag_IPSecsecprotocols" />
      </node>
    </node>
    <node label="Using Internet Protocol security" >
      <node label="Winteacher.com Using Internet Protocol security  " url="PART2/IPSEC_PIC/Using_Internet_Protocol_security/using_ipsec.htm" >
        <node label="H2_358266195" url="PART2/IPSEC_PIC/Using_Internet_Protocol_security/using_ipsec.htm#H2_358266195" />
        <node label="a_sag_IPSeckeyexchgsm" url="PART2/IPSEC_PIC/Using_Internet_Protocol_security/using_ipsec.htm#a_sag_IPSeckeyexchgsm" />
        <node label="a_sag_IPSecfeatures" url="PART2/IPSEC_PIC/Using_Internet_Protocol_security/using_ipsec.htm#a_sag_IPSecfeatures" />
        <node label="H2_358268026" url="PART2/IPSEC_PIC/Using_Internet_Protocol_security/using_ipsec.htm#H2_358268026" />
        <node label="H2_358271971" url="PART2/IPSEC_PIC/Using_Internet_Protocol_security/using_ipsec.htm#H2_358271971" />
        <node label="H3_358271853" url="PART2/IPSEC_PIC/Using_Internet_Protocol_security/using_ipsec.htm#H3_358271853" />
        <node label="H3_358271562" url="PART2/IPSEC_PIC/Using_Internet_Protocol_security/using_ipsec.htm#H3_358271562" />
        <node label="H2_358270951" url="PART2/IPSEC_PIC/Using_Internet_Protocol_security/using_ipsec.htm#H2_358270951" />
        <node label="H2_358266992" url="PART2/IPSEC_PIC/Using_Internet_Protocol_security/using_ipsec.htm#H2_358266992" />
        <node label="H2_358266682" url="PART2/IPSEC_PIC/Using_Internet_Protocol_security/using_ipsec.htm#H2_358266682" />
        <node label="H3_358267648" url="PART2/IPSEC_PIC/Using_Internet_Protocol_security/using_ipsec.htm#H3_358267648" />
        <node label="a_ipsec_key_exchange_sm" url="PART2/IPSEC_PIC/Using_Internet_Protocol_security/using_ipsec.htm#a_ipsec_key_exchange_sm" />
        <node label="H2_358266666" url="PART2/IPSEC_PIC/Using_Internet_Protocol_security/using_ipsec.htm#H2_358266666" />
        <node label="H2_358267736" url="PART2/IPSEC_PIC/Using_Internet_Protocol_security/using_ipsec.htm#H2_358267736" />
        <node label="H2_358268630" url="PART2/IPSEC_PIC/Using_Internet_Protocol_security/using_ipsec.htm#H2_358268630" />
        <node label="H3_358267191" url="PART2/IPSEC_PIC/Using_Internet_Protocol_security/using_ipsec.htm#H3_358267191" />
        <node label="a_sag_IPSeccommscene" url="PART2/IPSEC_PIC/Using_Internet_Protocol_security/using_ipsec.htm#a_sag_IPSeccommscene" />
        <node label="H3_358266660" url="PART2/IPSEC_PIC/Using_Internet_Protocol_security/using_ipsec.htm#H3_358266660" />
      </node>
    </node>
    <node label="Example-IPsec" >
      <node label="Winteacher.com IPsec ver4  (Example)   " url="PART2/IPSEC_PIC/Example-IPsec/example-ipsec.htm" />
    </node>
  </node>
  <node label="RRAS" >
    <node label="Step1" >
      <node label="RAS AND  RRAS ( Remote Access and TCP/IP and IPX )" url="PART2/RRAS_PIC/Step1/remoteaccess_tcpip_ipx2.htm" />
      <node label="RAS AND  RRAS ( Remote Access and TCP/IP and IPX )" url="PART2/RRAS_PIC/Step1/remoteaccess_tcpip_ipx.htm" />
      <node label="RAS AND  RRAS ( Remote Access Server Architecture )" url="PART2/RRAS_PIC/Step1/ras_architecture.htm" />
      <node label="RAS AND  RRAS ( Troubleshooting )" url="PART2/RRAS_PIC/Step1/troubleshooting.htm" />
      <node label="RAS AND  RRAS (Elements of Secure Remote Access)" url="PART2/RRAS_PIC/Step1/elements_secureremoteaccess_.htm" />
      <node label="RAS AND  RRAS (Managing Remote Access)" url="PART2/RRAS_PIC/Step1/managingremoteaccess.htm" />
      <node label="RAS AND  RRAS (PPP Authentication Protocols)" url="PART2/RRAS_PIC/Step1/PPP_AuthenticationProtocols.htm" />
      <node label="RAS AND  RRAS (Remote Access Overview )" url="PART2/RRAS_PIC/Step1/remote_access_overview_.htm" />
      <node label="RAS AND  RRAS (Remote Access Policies)" url="PART2/RRAS_PIC/Step1/remoteaccesspolicies.htm" />
    </node>
    <node label="Step2" >
      <node label="Introduction to RRAS" >
        <node label="OSPF" >
          <node label="RRAS  Introduction to RRAS (OSPF)" url="PART2/RRAS_PIC/Step2/Introduction_to_RRAS/OSPF/ospf.htm" />	
          <node label="RRAS  Introduction to RRAS (OSPF Operation)" url="PART2/RRAS_PIC/Step2/Introduction_to_RRAS/OSPF/OSPF_Operation.htm" />
          <node label="RRAS  Introduction to RRAS (OSPF Network Types)" url="PART2/RRAS_PIC/Step2/Introduction_to_RRAS/OSPF/OSPF_Network_Types.htm" />
          <node label="RRAS  Introduction to RRAS (Synchronizing the LSDB Through Adjacencies)" url="PART2/RRAS_PIC/Step2/Introduction_to_RRAS/OSPF/Synchronizing_LSDB.htm" />
		  <node label="RRAS  Introduction to RRAS (OSPF Communication on OSPF Networks)" url="PART2/RRAS_PIC/Step2/Introduction_to_RRAS/OSPF/OSPF_Communication.htm" />
          <node label="RRAS  Introduction to RRAS (OSPF Areas)" url="PART2/RRAS_PIC/Step2/Introduction_to_RRAS/OSPF/OSPFAreas.htm" />
          <node label="RRAS  Introduction to RRAS (Virtual Links)" url="PART2/RRAS_PIC/Step2/Introduction_to_RRAS/OSPF/Virtual_Links.htm" />

        </node>
        <node label="RIP" >
          <node label="RRAS  Introduction to RRAS ( RIP v1 , v2 )" url="PART2/RRAS_PIC/Step2/Introduction_to_RRAS/RIP_v1v2.htm" />
          <node label="RRAS  Introduction to RRAS (Windows 2000 as a RIP for IP Router)" url="PART2/RRAS_PIC/Step2/Introduction_to_RRAS/windows2000_rip.htm" />
          <node label="RRAS  Introduction to RRAS (Troubleshooting RIP for IP)" url="PART2/RRAS_PIC/Step2/Introduction_to_RRAS/Troubleshooting_RIP.htm" />
          <node label="RRAS  Introduction to RRAS (RIP for IP Operation)" url="PART2/RRAS_PIC/Step2/Introduction_to_RRAS/rip_ipoperation.htm" />
        </node>
        <node label="RRAS  Introduction to RRAS" url="PART2/RRAS_PIC/Step2/Introduction_to_RRAS/introduction_rras.htm" />
      </node>
    </node>
    <node label="Winteacher.com Remote Access Server AND Routing  Remote Access Server User Guide  " url="PART2/RRAS_PIC/rrasmain.htm" />
  </node>
  <node label="TCPIP" >
    <node label="Other-htm" >
	   <node label="Commands" >
        <node label="TCP / IP  User Guide (ARP)   " url="PART2/TCPIP_PIC/Other-htm/Commands/arp.htm" />
        <node label="TCP / IP  User Guide (IPConfig)   " url="PART2/TCPIP_PIC/Other-htm/Commands/ipconfig.htm" />
        <node label="TCP / IP  User Guide (Nbtstat)   " url="PART2/TCPIP_PIC/Other-htm/Commands/nbtstat.htm" />
        <node label="TCP / IP  User Guide (Netdiag)   " url="PART2/TCPIP_PIC/Other-htm/Commands/netdiag.htm" />
        <node label="TCP / IP  User Guide (Netstat)   " url="PART2/TCPIP_PIC/Other-htm/Commands/netstat.htm" />
        <node label="TCP / IP  User Guide (Nslookup)   " url="PART2/TCPIP_PIC/Other-htm/Commands/nslookup.htm" />
        <node label="TCP / IP  User Guide (PathPing)   " url="PART2/TCPIP_PIC/Other-htm/Commands/pathping.htm" />
        <node label="TCP / IP  User Guide (Ping)   " url="PART2/TCPIP_PIC/Other-htm/Commands/ping.htm" />
        <node label="TCP / IP  User Guide (Route)   " url="PART2/TCPIP_PIC/Other-htm/Commands/route.htm" />
        <node label="TCP / IP  User Guide (Tracert)   " url="PART2/TCPIP_PIC/Other-htm/Commands/tracert.htm" />
      </node>
      <node label="Introduction to TCPIP" >
        <node label="TCP / IP  User Guide (ARR)   " url="PART2/TCPIP_PIC/Other-htm/IntroductiontoTCPIP/ARP.htm" />
        <node label="TCP / IP  User Guide (IP Addressing)   " url="PART2/TCPIP_PIC/Other-htm/IntroductiontoTCPIP/ip_addressing.htm" />
        <node label="TCP / IP  User Guide (IP Routing)   " url="PART2/TCPIP_PIC/Other-htm/IntroductiontoTCPIP/IPRouting.htm" />
        <node label="TCP / IP  User Guide (IP Routing_Unicast Routing Principles)   " url="PART2/TCPIP_PIC/Other-htm/IntroductiontoTCPIP/Unicast_Routing_Principles.htm" />
        <node label="TCP / IP  User Guide (Name Resolution)   " url="PART2/TCPIP_PIC/Other-htm/IntroductiontoTCPIP/NameResolution.htm" />
        <node label="TCP / IP  User Guide (Public and Private Addresses)   " url="PART2/TCPIP_PIC/Other-htm/IntroductiontoTCPIP/Public_Private.htm" />
        <node label="TCP / IP  User Guide (Subnetting requires a three step procedure)   " url="PART2/TCPIP_PIC/Other-htm/IntroductiontoTCPIP/ThreeStep.htm" />
        <node label="TCP / IP  User Guide (Supernetting and Classless Interdomain Routing)   " url="PART2/TCPIP_PIC/Other-htm/IntroductiontoTCPIP/Supernetting_CIDR.htm" />
        <node label="TCP / IP  User Guide (TCP/IP Protocol Architecture)   " url="PART2/TCPIP_PIC/Other-htm/IntroductiontoTCPIP/protocol_architecture.htm" >
          <node label="sag_tcpip_ovr_model" url="PART2/TCPIP_PIC/Other-htm/IntroductiontoTCPIP/protocol_architecture.htm#sag_tcpip_ovr_model" />
        </node>
        <node label="TCP / IP  User Guide (Variable Length Subnetting)   " url="PART2/TCPIP_PIC/Other-htm/IntroductiontoTCPIP/variable_length.htm" />
      </node>
      <node label="Troubleshooting" >
        <node label="TCP / IP  User Guide ( Resolves the Host name or NetBIOS name to an IP address)   " url="PART2/TCPIP_PIC/Other-htm/Troubleshooting/troubleshhoting_reinstalling.htm" />
        <node label="TCP / IP  User Guide (Cannot Connect to a Specific Server)   " url="PART2/TCPIP_PIC/Other-htm/Troubleshooting/troubleshooting_specificserver.htm" />
        <node label="TCP / IP  User Guide (Error 53)   " url="PART2/TCPIP_PIC/Other-htm/Troubleshooting/troubleshooting_error53.htm" />
        <node label="TCP / IP  User Guide (Test IP-to-MAC Address Resolution with ARP)   " url="PART2/TCPIP_PIC/Other-htm/Troubleshooting/troubleshooting_test_ip-to-mac_.htm" />
        <node label="TCP / IP  User Guide Cannot Connect to Remote Systems Using Host Name)   " url="PART2/TCPIP_PIC/Other-htm/Troubleshooting/troubleshooting_cannotconnect.htm" />
      </node>
      <node label="TCP / IP  User Guide ( Resolves the Host name or NetBIOS name to an IP address)   " url="PART2/TCPIP_PIC/Other-htm/Step1_Resolves.htm" />
      <node label="TCP / IP  User Guide ( Using the destination IP address and the IP routing table, TCP/IP determines the interface to use and the forwarding IP address.)" url="PART2/TCPIP_PIC/Other-htm/step1_local_remote.htm" />
    </node>
    <node label="Winteacher.com TCP / IP  User Guide  " url="PART2/TCPIP_PIC/TCPIP-main.htm" />
  </node>
  <node label="WINS" >
    <node label="WINTEACHER.COM  WINS_User guide" url="PART2/WINS_PIC/wins_main.htm" >
      <node label="355" url="PART2/WINS_PIC/wins_main.htm#355" />
      <node label="354" url="PART2/WINS_PIC/wins_main.htm#354" />
    </node>
    <node label="Introduction to WINS" >
      <node label="WINS Replication Partners_properties_Advanced-Tab  " url="PART2/WINS_PIC/Other_HTM/replication_partners_properties_advanced-tab.htm" />
      <node label="WINS Replication Partners_properties_General-Tab  " url="PART2/WINS_PIC/Other_HTM/replication_partners_properties_general-tab.htm" />
      <node label="WINS Replication Partners_properties_Pullreplication-Tab  " url="PART2/WINS_PIC/Other_HTM/replication_partners_properties_pullreplication-tab.htm" />
      <node label="WINS  Delete Static Mapping  " url="PART2/WINS_PIC/Other_HTM/delete_static_mapping.htm" />
      <node label="WINS  Static Mapping  " url="PART2/WINS_PIC/Other_HTM/static_mapping.htm" />
      <node label="WINS Tombstoned_Release_Active  " url="PART2/WINS_PIC/Other_HTM/tombstoned_release_active.htm" />
      <node label="WINS  Properties_ Database verification-Tab  " url="PART2/WINS_PIC/Other_HTM/wins__properties__database_verification-tab.htm" />
      <node label="WINS Properties_advance-Tab" url="PART2/WINS_PIC/Other_HTM/wins_properties_advance-tab.htm" />
      <node label="WINS Properties_general-Tab  " url="PART2/WINS_PIC/Other_HTM/wins_properties_general-tab.htm" />
      <node label="WINS Properties_intervals-Tab  " url="PART2/WINS_PIC/Other_HTM/wins_properties_intervals-tab.htm" >
        <node label="wins_extinctiontimeout" url="PART2/WINS_PIC/Other_HTM/wins_properties_intervals-tab.htm#wins_extinctiontimeout" />
        <node label="wins_extinctioninterval" url="PART2/WINS_PIC/Other_HTM/wins_properties_intervals-tab.htm#wins_extinctioninterval" />
        <node label="wins_renewalinterval" url="PART2/WINS_PIC/Other_HTM/wins_properties_intervals-tab.htm#wins_renewalinterval" />
        <node label="wins_verificationinterval" url="PART2/WINS_PIC/Other_HTM/wins_properties_intervals-tab.htm#wins_verificationinterval" />
      </node>
      <node label="WINS Replication Partners_properties_Pushreplication-Tab  " url="PART2/WINS_PIC/Other_HTM/replication_partners_properties_pushreplication-tab.htm" />
    </node>
  </node>
</node>


</tocdata>
